biobb_chemistry/__init__.py
biobb_chemistry/py.typed
biobb_chemistry/acpype/__init__.py
biobb_chemistry/acpype/acpype_convert_amber_to_gmx.py
biobb_chemistry/acpype/acpype_params_ac.py
biobb_chemistry/acpype/acpype_params_cns.py
biobb_chemistry/acpype/acpype_params_gmx.py
biobb_chemistry/acpype/acpype_params_gmx_opls.py
biobb_chemistry/acpype/common.py
biobb_chemistry/ambertools/__init__.py
biobb_chemistry/ambertools/common.py
biobb_chemistry/ambertools/reduce_add_hydrogens.py
biobb_chemistry/ambertools/reduce_remove_hydrogens.py
biobb_chemistry/babelm/__init__.py
biobb_chemistry/babelm/babel_add_hydrogens.py
biobb_chemistry/babelm/babel_convert.py
biobb_chemistry/babelm/babel_minimize.py
biobb_chemistry/babelm/babel_remove_hydrogens.py
biobb_chemistry/babelm/common.py
biobb_chemistry/test/__init__.py
biobb_chemistry-5.2.0.dist-info/licenses/LICENSE
biobb_chemistry-5.2.0.dist-info/METADATA
biobb_chemistry-5.2.0.dist-info/WHEEL
biobb_chemistry-5.2.0.dist-info/entry_points.txt
biobb_chemistry-5.2.0.dist-info/top_level.txt
biobb_chemistry-5.2.0.dist-info/RECORD
